sendgrid_backend/__init__.py
sendgrid_backend/mail.py
sendgrid_backend/signals.py
sendgrid_backend/util.py
sendgrid_backend/version.py
django_sendgrid_v5-1.2.3.dist-info/LICENSE
django_sendgrid_v5-1.2.3.dist-info/METADATA
django_sendgrid_v5-1.2.3.dist-info/WHEEL
django_sendgrid_v5-1.2.3.dist-info/top_level.txt
django_sendgrid_v5-1.2.3.dist-info/RECORD
