Metadata-Version: 2.1
Name: django-sendgrid-v5
Version: 1.2.3
Summary: An implementation of Django's EmailBackend compatible with sendgrid-python v5+
Home-page: https://github.com/sklarsa/django-sendgrid-v5
Author: Steven Sklar
Author-email: sklarsa@gmail.com
License: MIT
Keywords: django email sendgrid backend
Classifier: Intended Audience :: Developers
Classifier: Programming Language :: Python :: 3
Classifier: Programming Language :: Python :: 3.6
Classifier: Programming Language :: Python :: 3.7
Classifier: Programming Language :: Python :: 3.8
Classifier: Programming Language :: Python :: 3.9
License-File: LICENSE
